{
  "data": [
    {
      "movieId": 3,
      "imageURL": "https://ssl.pstatic.net/imgmovie/mdi/mit110/0720/72054_P102_101939.jpg",
      "title": "다크 나이트 : 라이즈",
      "rate": "5.0",
      "date": "2012 . 미국"
    },
    {
      "movieId": 5,
      "imageURL": "https://ssl.pstatic.net/imgmovie/mdi/mit110/1073/107306_P32_143922.jpg",
      "title": "버드맨",
      "rate": "5.0",
      "date": "2014 . 프랑스"
    },
    {
      "movieId": 5,
      "imageURL": "https://ssl.pstatic.net/imgmovie/mdi/mit110/1073/107306_P32_143922.jpg",
      "title": "버드맨",
      "rate": "5.0",
      "date": "2014 . 프랑스"
    },
    {
      "movieId": 10,
      "imageURL": "https://ssl.pstatic.net/imgmovie/mdi/mit110/1368/136842_P22_104948.jpg",
      "title": "빅쇼트",
      "rate": "5.0",
      "date": "2015 . 헝가리"
    },
    {
      "movieId": 11,
      "imageURL": "https://ssl.pstatic.net/imgmovie/mdi/mit110/0650/F5021-00.jpg",
      "title": "라따뚜이",
      "rate": "5.0",
      "date": "2007 . 한국"
    },
    {
      "movieId": 12,
      "imageURL": "https://ssl.pstatic.net/imgmovie/mdi/mit110/0190/A9074-00.jpg",
      "title": "가타카",
      "rate": "5.0",
      "date": "1997 . 미국"
    },
    {
      "movieId": 14,
      "imageURL": "https://ssl.pstatic.net/imgmovie/mdi/mit110/0720/72058_P27_161216.jpg",
      "title": "블랙 스완",
      "rate": "5.0",
      "date": "2010 . 미국"
    },
    {
      "movieId": 17,
      "imageURL": "https://ssl.pstatic.net/imgmovie/mdi/mit110/0531/53152_P36_140212.jpg",
      "title": "500일의 썸머",
      "rate": "5.0",
      "date": "2009 . 미역국"
    },
    {
      "movieId": 21,
      "imageURL": "https://ssl.pstatic.net/imgmovie/mdi/mit110/1349/134963_P15_094953.jpg",
      "title": "라라랜드",
      "rate": "5.0",
      "date": "2016 . 캐나다"
    },
    {
      "movieId": 23,
      "imageURL": "https://ssl.pstatic.net/imgmovie/mdi/mit110/0319/C1913-00.jpg",
      "title": "바닐라 스카이",
      "rate": "5.0",
      "date": "2001 . 캐나다"
    },
    {
      "movieId": 23,
      "imageURL": "https://ssl.pstatic.net/imgmovie/mdi/mit110/0319/C1913-00.jpg",
      "title": "바닐라 스카이",
      "rate": "5.0",
      "date": "2001 . 캐나다"
    },
    {
      "movieId": 25,
      "imageURL": "https://ssl.pstatic.net/imgmovie/mdi/mit110/0102/10250_P29_095824.jpg",
      "title": "해리가 샐리를 만났을 때",
      "rate": "5.0",
      "date": "1989 . 프랑스"
    },
    {
      "movieId": 34,
      "imageURL": "https://ssl.pstatic.net/imgmovie/mdi/mit110/0101/A0140-00.jpg",
      "title": "매드 맥스",
      "rate": "5.0",
      "date": "1979 . 독일"
    },
    {
      "movieId": 35,
      "imageURL": "https://ssl.pstatic.net/imgmovie/mdi/mit110/0525/52515_P98_100506.jpg",
      "title": "인셉션",
      "rate": "5.0",
      "date": "2010 . 한국"
    },
    {
      "movieId": 35,
      "imageURL": "https://ssl.pstatic.net/imgmovie/mdi/mit110/0525/52515_P98_100506.jpg",
      "title": "인셉션",
      "rate": "5.0",
      "date": "2010 . 한국"
    },
    {
      "movieId": 38,
      "imageURL": "https://ssl.pstatic.net/imgmovie/mdi/mit110/1363/136315_P16_142450.jpg",
      "title": "어벤져스: 인피니티 워",
      "rate": "5.0",
      "date": "2018 . 중국"
    },
    {
      "movieId": 41,
      "imageURL": "https://ssl.pstatic.net/imgmovie/mdi/mit110/0517/51777_P39_121351.jpg",
      "title": "월드워Z",
      "rate": "5.0",
      "date": "2013 . 캐나다"
    },
    {
      "movieId": 43,
      "imageURL": "https://ssl.pstatic.net/imgmovie/mdi/mit110/1063/106360_P18_104023.jpg",
      "title": "위대한 쇼맨",
      "rate": "5.0",
      "date": "2017 . 미역국"
    },
    {
      "movieId": 43,
      "imageURL": "https://ssl.pstatic.net/imgmovie/mdi/mit110/1063/106360_P18_104023.jpg",
      "title": "위대한 쇼맨",
      "rate": "5.0",
      "date": "2017 . 미역국"
    },
    {
      "movieId": 49,
      "imageURL": "https://ssl.pstatic.net/imgmovie/mdi/mit110/0394/39440_P18_111613.jpg",
      "title": "이프 온리",
      "rate": "5.0",
      "date": "2004 . 한국"
    },
    {
      "movieId": 52,
      "imageURL": "https://ssl.pstatic.net/imgmovie/mdi/mit110/0754/75426_P21_180036.jpg",
      "title": "데드풀",
      "rate": "5.0",
      "date": "2016 . 프랑스"
    },
    {
      "movieId": 54,
      "imageURL": "https://ssl.pstatic.net/imgmovie/mdi/mit110/0397/C9708-00.jpg",
      "title": "콘스탄틴",
      "rate": "5.0",
      "date": "2005 . 독일"
    },
    {
      "movieId": 2,
      "imageURL": "https://ssl.pstatic.net/imgmovie/mdi/mit110/1588/158885_P29_102733.jpg",
      "title": "콜 미 바이 유어 네임",
      "rate": "4.5",
      "date": "2017 . 한국"
    },
    {
      "movieId": 5,
      "imageURL": "https://ssl.pstatic.net/imgmovie/mdi/mit110/1073/107306_P32_143922.jpg",
      "title": "버드맨",
      "rate": "4.5",
      "date": "2014 . 프랑스"
    },
    {
      "movieId": 5,
      "imageURL": "https://ssl.pstatic.net/imgmovie/mdi/mit110/1073/107306_P32_143922.jpg",
      "title": "버드맨",
      "rate": "4.5",
      "date": "2014 . 프랑스"
    },
    {
      "movieId": 6,
      "imageURL": "https://ssl.pstatic.net/imgmovie/mdi/mit110/1334/133424_P14_132012.jpg",
      "title": "데몰리션",
      "rate": "4.5",
      "date": "2015 . 미역국"
    },
    {
      "movieId": 16,
      "imageURL": "https://ssl.pstatic.net/imgmovie/mdi/mit110/1489/148909_P29_164758.jpg",
      "title": "더 페이버릿: 여왕의 여자",
      "rate": "4.5",
      "date": "2018 . 프랑스"
    },
    {
      "movieId": 19,
      "imageURL": "https://ssl.pstatic.net/imgmovie/mdi/mit110/1443/144379_P69_161321.jpg",
      "title": "러빙 빈센트",
      "rate": "4.5",
      "date": "2017 . 한국"
    },
    {
      "movieId": 20,
      "imageURL": "https://ssl.pstatic.net/imgmovie/mdi/mit110/1196/119632_P49_103013.jpg",
      "title": "위플래쉬",
      "rate": "4.5",
      "date": "2014 . 미역국"
    },
    {
      "movieId": 23,
      "imageURL": "https://ssl.pstatic.net/imgmovie/mdi/mit110/0319/C1913-00.jpg",
      "title": "바닐라 스카이",
      "rate": "4.5",
      "date": "2001 . 캐나다"
    },
    {
      "movieId": 26,
      "imageURL": "https://ssl.pstatic.net/imgmovie/mdi/mit110/1231/123118_P04_103601.jpg",
      "title": "떠나기 전 해야할 일",
      "rate": "4.5",
      "date": "2014 . 독일"
    },
    {
      "movieId": 29,
      "imageURL": "https://ssl.pstatic.net/imgmovie/mdi/mit110/0256/B5641-00.jpg",
      "title": "버팔로 66",
      "rate": "4.5",
      "date": "1998 . 헝가리"
    },
    {
      "movieId": 30,
      "imageURL": "https://ssl.pstatic.net/imgmovie/mdi/mit110/0203/20308_P12_105222.jpg",
      "title": "아키라",
      "rate": "4.5",
      "date": "1988 . 중국"
    },
    {
      "movieId": 32,
      "imageURL": "https://ssl.pstatic.net/imgmovie/mdi/mit110/0272/27260_P22_125837.jpg",
      "title": "파이트 클럽",
      "rate": "4.5",
      "date": "1999 . 헝가리"
    },
    {
      "movieId": 34,
      "imageURL": "https://ssl.pstatic.net/imgmovie/mdi/mit110/0101/A0140-00.jpg",
      "title": "매드 맥스",
      "rate": "4.5",
      "date": "1979 . 독일"
    },
    {
      "movieId": 41,
      "imageURL": "https://ssl.pstatic.net/imgmovie/mdi/mit110/0517/51777_P39_121351.jpg",
      "title": "월드워Z",
      "rate": "4.5",
      "date": "2013 . 캐나다"
    },
    {
      "movieId": 42,
      "imageURL": "https://ssl.pstatic.net/imgmovie/mdi/mit110/0100/10048_P14_143449.jpg",
      "title": "죽은 시인의 사회",
      "rate": "4.5",
      "date": "1989 . 영국"
    },
    {
      "movieId": 44,
      "imageURL": "https://ssl.pstatic.net/imgmovie/mdi/mit110/1501/150198_P60_142006.jpg",
      "title": "너의 이름은",
      "rate": "4.5",
      "date": "2016 . 캐나다"
    },
    {
      "movieId": 47,
      "imageURL": "https://ssl.pstatic.net/imgmovie/mdi/mit110/1903/190381_P52_115728.jpg",
      "title": "내가 죽던 날",
      "rate": "4.5",
      "date": "2020 . 중국"
    },
    {
      "movieId": 52,
      "imageURL": "https://ssl.pstatic.net/imgmovie/mdi/mit110/0754/75426_P21_180036.jpg",
      "title": "데드풀",
      "rate": "4.5",
      "date": "2016 . 프랑스"
    },
    {
      "movieId": 53,
      "imageURL": "https://ssl.pstatic.net/imgmovie/mdi/mit110/0171/17159_P12_153452.jpg",
      "title": "포레스트 검프",
      "rate": "4.5",
      "date": "1994 . 헝가리"
    },
    {
      "movieId": 7,
      "imageURL": "https://ssl.pstatic.net/imgmovie/mdi/mit110/1900/190010_P02_162156.jpg",
      "title": "테넷",
      "rate": "4.0",
      "date": "2020 . 독일"
    },
    {
      "movieId": 7,
      "imageURL": "https://ssl.pstatic.net/imgmovie/mdi/mit110/1900/190010_P02_162156.jpg",
      "title": "테넷",
      "rate": "4.0",
      "date": "2020 . 독일"
    },
    {
      "movieId": 8,
      "imageURL": "https://ssl.pstatic.net/imgmovie/mdi/mit110/0794/79422_P03_182813.jpg",
      "title": "엄청나게 시끄럽고 믿을 수 없게 가까운",
      "rate": "4.0",
      "date": "2011 . 한국"
    },
    {
      "movieId": 13,
      "imageURL": "https://ssl.pstatic.net/imgmovie/mdi/mit110/1717/171725_P18_175530.jpg",
      "title": "스파이더맨: 뉴 유니버스",
      "rate": "4.0",
      "date": "2018 . 캐나다"
    },
    {
      "movieId": 14,
      "imageURL": "https://ssl.pstatic.net/imgmovie/mdi/mit110/0720/72058_P27_161216.jpg",
      "title": "블랙 스완",
      "rate": "4.0",
      "date": "2010 . 미국"
    },
    {
      "movieId": 15,
      "imageURL": "https://ssl.pstatic.net/imgmovie/mdi/mit110/1526/152694_P17_101815.jpg",
      "title": "킬링 디어",
      "rate": "4.0",
      "date": "2017 . 미역국"
    },
    {
      "movieId": 20,
      "imageURL": "https://ssl.pstatic.net/imgmovie/mdi/mit110/1196/119632_P49_103013.jpg",
      "title": "위플래쉬",
      "rate": "4.0",
      "date": "2014 . 미역국"
    },
    {
      "movieId": 22,
      "imageURL": "https://ssl.pstatic.net/imgmovie/mdi/mit110/0421/D2117-00.jpg",
      "title": "007 카지노 로얄",
      "rate": "4.0",
      "date": "2006 . 한국"
    },
    {
      "movieId": 24,
      "imageURL": "https://ssl.pstatic.net/imgmovie/mdi/mit110/0193/A9302-00.jpg",
      "title": "붉은 돼지",
      "rate": "4.0",
      "date": "1992 . 미국"
    },
    {
      "movieId": 25,
      "imageURL": "https://ssl.pstatic.net/imgmovie/mdi/mit110/0102/10250_P29_095824.jpg",
      "title": "해리가 샐리를 만났을 때",
      "rate": "4.0",
      "date": "1989 . 프랑스"
    },
    {
      "movieId": 31,
      "imageURL": "https://ssl.pstatic.net/imgmovie/mdi/mit110/0378/C7888-01.jpg",
      "title": "아는 여자",
      "rate": "4.0",
      "date": "2004 . 영국"
    },
    {
      "movieId": 32,
      "imageURL": "https://ssl.pstatic.net/imgmovie/mdi/mit110/0272/27260_P22_125837.jpg",
      "title": "파이트 클럽",
      "rate": "4.0",
      "date": "1999 . 헝가리"
    },
    {
      "movieId": 33,
      "imageURL": "https://ssl.pstatic.net/imgmovie/mdi/mit110/0384/38444_P53_180242.jpg",
      "title": "이터널 선샤인",
      "rate": "4.0",
      "date": "2004 . 미역국"
    },
    {
      "movieId": 34,
      "imageURL": "https://ssl.pstatic.net/imgmovie/mdi/mit110/0101/A0140-00.jpg",
      "title": "매드 맥스",
      "rate": "4.0",
      "date": "1979 . 독일"
    },
    {
      "movieId": 41,
      "imageURL": "https://ssl.pstatic.net/imgmovie/mdi/mit110/0517/51777_P39_121351.jpg",
      "title": "월드워Z",
      "rate": "4.0",
      "date": "2013 . 캐나다"
    },
    {
      "movieId": 42,
      "imageURL": "https://ssl.pstatic.net/imgmovie/mdi/mit110/0100/10048_P14_143449.jpg",
      "title": "죽은 시인의 사회",
      "rate": "4.0",
      "date": "1989 . 영국"
    },
    {
      "movieId": 51,
      "imageURL": "https://ssl.pstatic.net/imgmovie/mdi/mit110/0445/D4529-00.jpg",
      "title": "해바라기",
      "rate": "4.0",
      "date": "2006 . 프랑스"
    },
    {
      "movieId": 2,
      "imageURL": "https://ssl.pstatic.net/imgmovie/mdi/mit110/1588/158885_P29_102733.jpg",
      "title": "콜 미 바이 유어 네임",
      "rate": "3.5",
      "date": "2017 . 한국"
    },
    {
      "movieId": 3,
      "imageURL": "https://ssl.pstatic.net/imgmovie/mdi/mit110/0720/72054_P102_101939.jpg",
      "title": "다크 나이트 : 라이즈",
      "rate": "3.5",
      "date": "2012 . 미국"
    },
    {
      "movieId": 4,
      "imageURL": "https://ssl.pstatic.net/imgmovie/mdi/mit110/0486/48690_P03_181555.jpg",
      "title": "맨 프럼 어스",
      "rate": "3.5",
      "date": "2007 . 미국"
    },
    {
      "movieId": 5,
      "imageURL": "https://ssl.pstatic.net/imgmovie/mdi/mit110/1073/107306_P32_143922.jpg",
      "title": "버드맨",
      "rate": "3.5",
      "date": "2014 . 프랑스"
    },
    {
      "movieId": 9,
      "imageURL": "https://ssl.pstatic.net/imgmovie/mdi/mit110/0193/A9303-00.jpg",
      "title": "모노노케 히메",
      "rate": "3.5",
      "date": "1997 . 프랑스"
    },
    {
      "movieId": 15,
      "imageURL": "https://ssl.pstatic.net/imgmovie/mdi/mit110/1526/152694_P17_101815.jpg",
      "title": "킬링 디어",
      "rate": "3.5",
      "date": "2017 . 미역국"
    },
    {
      "movieId": 16,
      "imageURL": "https://ssl.pstatic.net/imgmovie/mdi/mit110/1489/148909_P29_164758.jpg",
      "title": "더 페이버릿: 여왕의 여자",
      "rate": "3.5",
      "date": "2018 . 프랑스"
    },
    {
      "movieId": 17,
      "imageURL": "https://ssl.pstatic.net/imgmovie/mdi/mit110/0531/53152_P36_140212.jpg",
      "title": "500일의 썸머",
      "rate": "3.5",
      "date": "2009 . 미역국"
    },
    {
      "movieId": 17,
      "imageURL": "https://ssl.pstatic.net/imgmovie/mdi/mit110/0531/53152_P36_140212.jpg",
      "title": "500일의 썸머",
      "rate": "3.5",
      "date": "2009 . 미역국"
    },
    {
      "movieId": 18,
      "imageURL": "https://ssl.pstatic.net/imgmovie/mdi/mit110/1724/172425_P04_130843.jpg",
      "title": "서치",
      "rate": "3.5",
      "date": "2017 . 독일"
    },
    {
      "movieId": 29,
      "imageURL": "https://ssl.pstatic.net/imgmovie/mdi/mit110/0256/B5641-00.jpg",
      "title": "버팔로 66",
      "rate": "3.5",
      "date": "1998 . 헝가리"
    },
    {
      "movieId": 38,
      "imageURL": "https://ssl.pstatic.net/imgmovie/mdi/mit110/1363/136315_P16_142450.jpg",
      "title": "어벤져스: 인피니티 워",
      "rate": "3.5",
      "date": "2018 . 중국"
    },
    {
      "movieId": 39,
      "imageURL": "https://ssl.pstatic.net/imgmovie/mdi/mit110/0356/35626_P00_164158.jpg",
      "title": "8 마일",
      "rate": "3.5",
      "date": "2002 . 프랑스"
    },
    {
      "movieId": 45,
      "imageURL": "https://ssl.pstatic.net/imgmovie/mdi/mit110/0292/B9276-03.jpg",
      "title": "페어런트 트랩",
      "rate": "3.5",
      "date": "1998 . 캐나다"
    },
    {
      "movieId": 45,
      "imageURL": "https://ssl.pstatic.net/imgmovie/mdi/mit110/0292/B9276-03.jpg",
      "title": "페어런트 트랩",
      "rate": "3.5",
      "date": "1998 . 캐나다"
    },
    {
      "movieId": 46,
      "imageURL": "https://ssl.pstatic.net/imgmovie/mdi/mit110/0326/32686_P47_105154.jpg",
      "title": "센과 치히로의 행방불명",
      "rate": "3.5",
      "date": "2001 . 중국"
    },
    {
      "movieId": 47,
      "imageURL": "https://ssl.pstatic.net/imgmovie/mdi/mit110/1903/190381_P52_115728.jpg",
      "title": "내가 죽던 날",
      "rate": "3.5",
      "date": "2020 . 중국"
    },
    {
      "movieId": 49,
      "imageURL": "https://ssl.pstatic.net/imgmovie/mdi/mit110/0394/39440_P18_111613.jpg",
      "title": "이프 온리",
      "rate": "3.5",
      "date": "2004 . 한국"
    },
    {
      "movieId": 49,
      "imageURL": "https://ssl.pstatic.net/imgmovie/mdi/mit110/0394/39440_P18_111613.jpg",
      "title": "이프 온리",
      "rate": "3.5",
      "date": "2004 . 한국"
    },
    {
      "movieId": 52,
      "imageURL": "https://ssl.pstatic.net/imgmovie/mdi/mit110/0754/75426_P21_180036.jpg",
      "title": "데드풀",
      "rate": "3.5",
      "date": "2016 . 프랑스"
    },
    {
      "movieId": 54,
      "imageURL": "https://ssl.pstatic.net/imgmovie/mdi/mit110/0397/C9708-00.jpg",
      "title": "콘스탄틴",
      "rate": "3.5",
      "date": "2005 . 독일"
    },
    {
      "movieId": 3,
      "imageURL": "https://ssl.pstatic.net/imgmovie/mdi/mit110/0720/72054_P102_101939.jpg",
      "title": "다크 나이트 : 라이즈",
      "rate": "3.0",
      "date": "2012 . 미국"
    },
    {
      "movieId": 7,
      "imageURL": "https://ssl.pstatic.net/imgmovie/mdi/mit110/1900/190010_P02_162156.jpg",
      "title": "테넷",
      "rate": "3.0",
      "date": "2020 . 독일"
    },
    {
      "movieId": 10,
      "imageURL": "https://ssl.pstatic.net/imgmovie/mdi/mit110/1368/136842_P22_104948.jpg",
      "title": "빅쇼트",
      "rate": "3.0",
      "date": "2015 . 헝가리"
    },
    {
      "movieId": 14,
      "imageURL": "https://ssl.pstatic.net/imgmovie/mdi/mit110/0720/72058_P27_161216.jpg",
      "title": "블랙 스완",
      "rate": "3.0",
      "date": "2010 . 미국"
    },
    {
      "movieId": 22,
      "imageURL": "https://ssl.pstatic.net/imgmovie/mdi/mit110/0421/D2117-00.jpg",
      "title": "007 카지노 로얄",
      "rate": "3.0",
      "date": "2006 . 한국"
    },
    {
      "movieId": 24,
      "imageURL": "https://ssl.pstatic.net/imgmovie/mdi/mit110/0193/A9302-00.jpg",
      "title": "붉은 돼지",
      "rate": "3.0",
      "date": "1992 . 미국"
    },
    {
      "movieId": 25,
      "imageURL": "https://ssl.pstatic.net/imgmovie/mdi/mit110/0102/10250_P29_095824.jpg",
      "title": "해리가 샐리를 만났을 때",
      "rate": "3.0",
      "date": "1989 . 프랑스"
    },
    {
      "movieId": 26,
      "imageURL": "https://ssl.pstatic.net/imgmovie/mdi/mit110/1231/123118_P04_103601.jpg",
      "title": "떠나기 전 해야할 일",
      "rate": "3.0",
      "date": "2014 . 독일"
    },
    {
      "movieId": 30,
      "imageURL": "https://ssl.pstatic.net/imgmovie/mdi/mit110/0203/20308_P12_105222.jpg",
      "title": "아키라",
      "rate": "3.0",
      "date": "1988 . 중국"
    },
    {
      "movieId": 35,
      "imageURL": "https://ssl.pstatic.net/imgmovie/mdi/mit110/0525/52515_P98_100506.jpg",
      "title": "인셉션",
      "rate": "3.0",
      "date": "2010 . 한국"
    },
    {
      "movieId": 38,
      "imageURL": "https://ssl.pstatic.net/imgmovie/mdi/mit110/1363/136315_P16_142450.jpg",
      "title": "어벤져스: 인피니티 워",
      "rate": "3.0",
      "date": "2018 . 중국"
    },
    {
      "movieId": 40,
      "imageURL": "https://ssl.pstatic.net/imgmovie/mdi/mit110/1196/119632_P49_103013.jpg",
      "title": "위플래쉬",
      "rate": "3.0",
      "date": "2014 . 한국"
    },
    {
      "movieId": 43,
      "imageURL": "https://ssl.pstatic.net/imgmovie/mdi/mit110/1063/106360_P18_104023.jpg",
      "title": "위대한 쇼맨",
      "rate": "3.0",
      "date": "2017 . 미역국"
    },
    {
      "movieId": 44,
      "imageURL": "https://ssl.pstatic.net/imgmovie/mdi/mit110/1501/150198_P60_142006.jpg",
      "title": "너의 이름은",
      "rate": "3.0",
      "date": "2016 . 캐나다"
    },
    {
      "movieId": 50,
      "imageURL": "https://ssl.pstatic.net/imgmovie/mdi/mit110/0368/C6858-00.jpg",
      "title": "브루스 올마이티",
      "rate": "3.0",
      "date": "2003 . 중국"
    },
    {
      "movieId": 51,
      "imageURL": "https://ssl.pstatic.net/imgmovie/mdi/mit110/0445/D4529-00.jpg",
      "title": "해바라기",
      "rate": "3.0",
      "date": "2006 . 프랑스"
    },
    {
      "movieId": 3,
      "imageURL": "https://ssl.pstatic.net/imgmovie/mdi/mit110/0720/72054_P102_101939.jpg",
      "title": "다크 나이트 : 라이즈",
      "rate": "2.5",
      "date": "2012 . 미국"
    },
    {
      "movieId": 8,
      "imageURL": "https://ssl.pstatic.net/imgmovie/mdi/mit110/0794/79422_P03_182813.jpg",
      "title": "엄청나게 시끄럽고 믿을 수 없게 가까운",
      "rate": "2.5",
      "date": "2011 . 한국"
    },
    {
      "movieId": 9,
      "imageURL": "https://ssl.pstatic.net/imgmovie/mdi/mit110/0193/A9303-00.jpg",
      "title": "모노노케 히메",
      "rate": "2.5",
      "date": "1997 . 프랑스"
    },
    {
      "movieId": 15,
      "imageURL": "https://ssl.pstatic.net/imgmovie/mdi/mit110/1526/152694_P17_101815.jpg",
      "title": "킬링 디어",
      "rate": "2.5",
      "date": "2017 . 미역국"
    },
    {
      "movieId": 16,
      "imageURL": "https://ssl.pstatic.net/imgmovie/mdi/mit110/1489/148909_P29_164758.jpg",
      "title": "더 페이버릿: 여왕의 여자",
      "rate": "2.5",
      "date": "2018 . 프랑스"
    },
    {
      "movieId": 18,
      "imageURL": "https://ssl.pstatic.net/imgmovie/mdi/mit110/1724/172425_P04_130843.jpg",
      "title": "서치",
      "rate": "2.5",
      "date": "2017 . 독일"
    },
    {
      "movieId": 19,
      "imageURL": "https://ssl.pstatic.net/imgmovie/mdi/mit110/1443/144379_P69_161321.jpg",
      "title": "러빙 빈센트",
      "rate": "2.5",
      "date": "2017 . 한국"
    },
    {
      "movieId": 33,
      "imageURL": "https://ssl.pstatic.net/imgmovie/mdi/mit110/0384/38444_P53_180242.jpg",
      "title": "이터널 선샤인",
      "rate": "2.5",
      "date": "2004 . 미역국"
    },
    {
      "movieId": 35,
      "imageURL": "https://ssl.pstatic.net/imgmovie/mdi/mit110/0525/52515_P98_100506.jpg",
      "title": "인셉션",
      "rate": "2.5",
      "date": "2010 . 한국"
    },
    {
      "movieId": 37,
      "imageURL": "https://ssl.pstatic.net/imgmovie/mdi/mit110/1369/136900_P57_104126.jpg",
      "title": "어벤져스: 엔드게임",
      "rate": "2.5",
      "date": "2019 . 영국"
    },
    {
      "movieId": 38,
      "imageURL": "https://ssl.pstatic.net/imgmovie/mdi/mit110/1363/136315_P16_142450.jpg",
      "title": "어벤져스: 인피니티 워",
      "rate": "2.5",
      "date": "2018 . 중국"
    },
    {
      "movieId": 40,
      "imageURL": "https://ssl.pstatic.net/imgmovie/mdi/mit110/1196/119632_P49_103013.jpg",
      "title": "위플래쉬",
      "rate": "2.5",
      "date": "2014 . 한국"
    },
    {
      "movieId": 45,
      "imageURL": "https://ssl.pstatic.net/imgmovie/mdi/mit110/0292/B9276-03.jpg",
      "title": "페어런트 트랩",
      "rate": "2.5",
      "date": "1998 . 캐나다"
    },
    {
      "movieId": 46,
      "imageURL": "https://ssl.pstatic.net/imgmovie/mdi/mit110/0326/32686_P47_105154.jpg",
      "title": "센과 치히로의 행방불명",
      "rate": "2.5",
      "date": "2001 . 중국"
    },
    {
      "movieId": 2,
      "imageURL": "https://ssl.pstatic.net/imgmovie/mdi/mit110/1588/158885_P29_102733.jpg",
      "title": "콜 미 바이 유어 네임",
      "rate": "2.0",
      "date": "2017 . 한국"
    },
    {
      "movieId": 9,
      "imageURL": "https://ssl.pstatic.net/imgmovie/mdi/mit110/0193/A9303-00.jpg",
      "title": "모노노케 히메",
      "rate": "2.0",
      "date": "1997 . 프랑스"
    },
    {
      "movieId": 11,
      "imageURL": "https://ssl.pstatic.net/imgmovie/mdi/mit110/0650/F5021-00.jpg",
      "title": "라따뚜이",
      "rate": "2.0",
      "date": "2007 . 한국"
    },
    {
      "movieId": 11,
      "imageURL": "https://ssl.pstatic.net/imgmovie/mdi/mit110/0650/F5021-00.jpg",
      "title": "라따뚜이",
      "rate": "2.0",
      "date": "2007 . 한국"
    },
    {
      "movieId": 18,
      "imageURL": "https://ssl.pstatic.net/imgmovie/mdi/mit110/1724/172425_P04_130843.jpg",
      "title": "서치",
      "rate": "2.0",
      "date": "2017 . 독일"
    },
    {
      "movieId": 19,
      "imageURL": "https://ssl.pstatic.net/imgmovie/mdi/mit110/1443/144379_P69_161321.jpg",
      "title": "러빙 빈센트",
      "rate": "2.0",
      "date": "2017 . 한국"
    },
    {
      "movieId": 20,
      "imageURL": "https://ssl.pstatic.net/imgmovie/mdi/mit110/1196/119632_P49_103013.jpg",
      "title": "위플래쉬",
      "rate": "2.0",
      "date": "2014 . 미역국"
    },
    {
      "movieId": 21,
      "imageURL": "https://ssl.pstatic.net/imgmovie/mdi/mit110/1349/134963_P15_094953.jpg",
      "title": "라라랜드",
      "rate": "2.0",
      "date": "2016 . 캐나다"
    },
    {
      "movieId": 21,
      "imageURL": "https://ssl.pstatic.net/imgmovie/mdi/mit110/1349/134963_P15_094953.jpg",
      "title": "라라랜드",
      "rate": "2.0",
      "date": "2016 . 캐나다"
    },
    {
      "movieId": 24,
      "imageURL": "https://ssl.pstatic.net/imgmovie/mdi/mit110/0193/A9302-00.jpg",
      "title": "붉은 돼지",
      "rate": "2.0",
      "date": "1992 . 미국"
    },
    {
      "movieId": 26,
      "imageURL": "https://ssl.pstatic.net/imgmovie/mdi/mit110/1231/123118_P04_103601.jpg",
      "title": "떠나기 전 해야할 일",
      "rate": "2.0",
      "date": "2014 . 독일"
    },
    {
      "movieId": 27,
      "imageURL": "https://ssl.pstatic.net/imgmovie/mdi/mit110/0882/88227_P24_113936.jpg",
      "title": "블레이드 러너 : 2049",
      "rate": "2.0",
      "date": "2017 . 영국"
    },
    {
      "movieId": 28,
      "imageURL": "https://ssl.pstatic.net/imgmovie/mdi/mit110/0274/27404_P19_121928.jpg",
      "title": "4월 이야기",
      "rate": "2.0",
      "date": "1998 . 미국"
    },
    {
      "movieId": 28,
      "imageURL": "https://ssl.pstatic.net/imgmovie/mdi/mit110/0274/27404_P19_121928.jpg",
      "title": "4월 이야기",
      "rate": "2.0",
      "date": "1998 . 미국"
    },
    {
      "movieId": 31,
      "imageURL": "https://ssl.pstatic.net/imgmovie/mdi/mit110/0378/C7888-01.jpg",
      "title": "아는 여자",
      "rate": "2.0",
      "date": "2004 . 영국"
    },
    {
      "movieId": 38,
      "imageURL": "https://ssl.pstatic.net/imgmovie/mdi/mit110/1363/136315_P16_142450.jpg",
      "title": "어벤져스: 인피니티 워",
      "rate": "2.0",
      "date": "2018 . 중국"
    },
    {
      "movieId": 39,
      "imageURL": "https://ssl.pstatic.net/imgmovie/mdi/mit110/0356/35626_P00_164158.jpg",
      "title": "8 마일",
      "rate": "2.0",
      "date": "2002 . 프랑스"
    },
    {
      "movieId": 41,
      "imageURL": "https://ssl.pstatic.net/imgmovie/mdi/mit110/0517/51777_P39_121351.jpg",
      "title": "월드워Z",
      "rate": "2.0",
      "date": "2013 . 캐나다"
    },
    {
      "movieId": 45,
      "imageURL": "https://ssl.pstatic.net/imgmovie/mdi/mit110/0292/B9276-03.jpg",
      "title": "페어런트 트랩",
      "rate": "2.0",
      "date": "1998 . 캐나다"
    },
    {
      "movieId": 46,
      "imageURL": "https://ssl.pstatic.net/imgmovie/mdi/mit110/0326/32686_P47_105154.jpg",
      "title": "센과 치히로의 행방불명",
      "rate": "2.0",
      "date": "2001 . 중국"
    },
    {
      "movieId": 47,
      "imageURL": "https://ssl.pstatic.net/imgmovie/mdi/mit110/1903/190381_P52_115728.jpg",
      "title": "내가 죽던 날",
      "rate": "2.0",
      "date": "2020 . 중국"
    },
    {
      "movieId": 49,
      "imageURL": "https://ssl.pstatic.net/imgmovie/mdi/mit110/0394/39440_P18_111613.jpg",
      "title": "이프 온리",
      "rate": "2.0",
      "date": "2004 . 한국"
    },
    {
      "movieId": 51,
      "imageURL": "https://ssl.pstatic.net/imgmovie/mdi/mit110/0445/D4529-00.jpg",
      "title": "해바라기",
      "rate": "2.0",
      "date": "2006 . 프랑스"
    },
    {
      "movieId": 6,
      "imageURL": "https://ssl.pstatic.net/imgmovie/mdi/mit110/1334/133424_P14_132012.jpg",
      "title": "데몰리션",
      "rate": "1.5",
      "date": "2015 . 미역국"
    },
    {
      "movieId": 15,
      "imageURL": "https://ssl.pstatic.net/imgmovie/mdi/mit110/1526/152694_P17_101815.jpg",
      "title": "킬링 디어",
      "rate": "1.5",
      "date": "2017 . 미역국"
    },
    {
      "movieId": 22,
      "imageURL": "https://ssl.pstatic.net/imgmovie/mdi/mit110/0421/D2117-00.jpg",
      "title": "007 카지노 로얄",
      "rate": "1.5",
      "date": "2006 . 한국"
    },
    {
      "movieId": 23,
      "imageURL": "https://ssl.pstatic.net/imgmovie/mdi/mit110/0319/C1913-00.jpg",
      "title": "바닐라 스카이",
      "rate": "1.5",
      "date": "2001 . 캐나다"
    },
    {
      "movieId": 31,
      "imageURL": "https://ssl.pstatic.net/imgmovie/mdi/mit110/0378/C7888-01.jpg",
      "title": "아는 여자",
      "rate": "1.5",
      "date": "2004 . 영국"
    },
    {
      "movieId": 32,
      "imageURL": "https://ssl.pstatic.net/imgmovie/mdi/mit110/0272/27260_P22_125837.jpg",
      "title": "파이트 클럽",
      "rate": "1.5",
      "date": "1999 . 헝가리"
    },
    {
      "movieId": 39,
      "imageURL": "https://ssl.pstatic.net/imgmovie/mdi/mit110/0356/35626_P00_164158.jpg",
      "title": "8 마일",
      "rate": "1.5",
      "date": "2002 . 프랑스"
    },
    {
      "movieId": 46,
      "imageURL": "https://ssl.pstatic.net/imgmovie/mdi/mit110/0326/32686_P47_105154.jpg",
      "title": "센과 치히로의 행방불명",
      "rate": "1.5",
      "date": "2001 . 중국"
    },
    {
      "movieId": 47,
      "imageURL": "https://ssl.pstatic.net/imgmovie/mdi/mit110/1903/190381_P52_115728.jpg",
      "title": "내가 죽던 날",
      "rate": "1.5",
      "date": "2020 . 중국"
    },
    {
      "movieId": 55,
      "imageURL": "https://ssl.pstatic.net/imgmovie/mdi/mit110/0505/50598_P68_080618.jpg",
      "title": "A-특공대",
      "rate": "1.5",
      "date": "2010 . 헝가리"
    },
    {
      "movieId": 4,
      "imageURL": "https://ssl.pstatic.net/imgmovie/mdi/mit110/0486/48690_P03_181555.jpg",
      "title": "맨 프럼 어스",
      "rate": "1.0",
      "date": "2007 . 미국"
    },
    {
      "movieId": 7,
      "imageURL": "https://ssl.pstatic.net/imgmovie/mdi/mit110/1900/190010_P02_162156.jpg",
      "title": "테넷",
      "rate": "1.0",
      "date": "2020 . 독일"
    },
    {
      "movieId": 12,
      "imageURL": "https://ssl.pstatic.net/imgmovie/mdi/mit110/0190/A9074-00.jpg",
      "title": "가타카",
      "rate": "1.0",
      "date": "1997 . 미국"
    },
    {
      "movieId": 12,
      "imageURL": "https://ssl.pstatic.net/imgmovie/mdi/mit110/0190/A9074-00.jpg",
      "title": "가타카",
      "rate": "1.0",
      "date": "1997 . 미국"
    },
    {
      "movieId": 14,
      "imageURL": "https://ssl.pstatic.net/imgmovie/mdi/mit110/0720/72058_P27_161216.jpg",
      "title": "블랙 스완",
      "rate": "1.0",
      "date": "2010 . 미국"
    },
    {
      "movieId": 21,
      "imageURL": "https://ssl.pstatic.net/imgmovie/mdi/mit110/1349/134963_P15_094953.jpg",
      "title": "라라랜드",
      "rate": "1.0",
      "date": "2016 . 캐나다"
    },
    {
      "movieId": 22,
      "imageURL": "https://ssl.pstatic.net/imgmovie/mdi/mit110/0421/D2117-00.jpg",
      "title": "007 카지노 로얄",
      "rate": "1.0",
      "date": "2006 . 한국"
    },
    {
      "movieId": 26,
      "imageURL": "https://ssl.pstatic.net/imgmovie/mdi/mit110/1231/123118_P04_103601.jpg",
      "title": "떠나기 전 해야할 일",
      "rate": "1.0",
      "date": "2014 . 독일"
    },
    {
      "movieId": 29,
      "imageURL": "https://ssl.pstatic.net/imgmovie/mdi/mit110/0256/B5641-00.jpg",
      "title": "버팔로 66",
      "rate": "1.0",
      "date": "1998 . 헝가리"
    },
    {
      "movieId": 37,
      "imageURL": "https://ssl.pstatic.net/imgmovie/mdi/mit110/1369/136900_P57_104126.jpg",
      "title": "어벤져스: 엔드게임",
      "rate": "1.0",
      "date": "2019 . 영국"
    },
    {
      "movieId": 39,
      "imageURL": "https://ssl.pstatic.net/imgmovie/mdi/mit110/0356/35626_P00_164158.jpg",
      "title": "8 마일",
      "rate": "1.0",
      "date": "2002 . 프랑스"
    },
    {
      "movieId": 39,
      "imageURL": "https://ssl.pstatic.net/imgmovie/mdi/mit110/0356/35626_P00_164158.jpg",
      "title": "8 마일",
      "rate": "1.0",
      "date": "2002 . 프랑스"
    },
    {
      "movieId": 45,
      "imageURL": "https://ssl.pstatic.net/imgmovie/mdi/mit110/0292/B9276-03.jpg",
      "title": "페어런트 트랩",
      "rate": "1.0",
      "date": "1998 . 캐나다"
    },
    {
      "movieId": 51,
      "imageURL": "https://ssl.pstatic.net/imgmovie/mdi/mit110/0445/D4529-00.jpg",
      "title": "해바라기",
      "rate": "1.0",
      "date": "2006 . 프랑스"
    },
    {
      "movieId": 3,
      "imageURL": "https://ssl.pstatic.net/imgmovie/mdi/mit110/0720/72054_P102_101939.jpg",
      "title": "다크 나이트 : 라이즈",
      "rate": "0.5",
      "date": "2012 . 미국"
    },
    {
      "movieId": 7,
      "imageURL": "https://ssl.pstatic.net/imgmovie/mdi/mit110/1900/190010_P02_162156.jpg",
      "title": "테넷",
      "rate": "0.5",
      "date": "2020 . 독일"
    },
    {
      "movieId": 8,
      "imageURL": "https://ssl.pstatic.net/imgmovie/mdi/mit110/0794/79422_P03_182813.jpg",
      "title": "엄청나게 시끄럽고 믿을 수 없게 가까운",
      "rate": "0.5",
      "date": "2011 . 한국"
    },
    {
      "movieId": 11,
      "imageURL": "https://ssl.pstatic.net/imgmovie/mdi/mit110/0650/F5021-00.jpg",
      "title": "라따뚜이",
      "rate": "0.5",
      "date": "2007 . 한국"
    },
    {
      "movieId": 12,
      "imageURL": "https://ssl.pstatic.net/imgmovie/mdi/mit110/0190/A9074-00.jpg",
      "title": "가타카",
      "rate": "0.5",
      "date": "1997 . 미국"
    },
    {
      "movieId": 13,
      "imageURL": "https://ssl.pstatic.net/imgmovie/mdi/mit110/1717/171725_P18_175530.jpg",
      "title": "스파이더맨: 뉴 유니버스",
      "rate": "0.5",
      "date": "2018 . 캐나다"
    },
    {
      "movieId": 13,
      "imageURL": "https://ssl.pstatic.net/imgmovie/mdi/mit110/1717/171725_P18_175530.jpg",
      "title": "스파이더맨: 뉴 유니버스",
      "rate": "0.5",
      "date": "2018 . 캐나다"
    },
    {
      "movieId": 14,
      "imageURL": "https://ssl.pstatic.net/imgmovie/mdi/mit110/0720/72058_P27_161216.jpg",
      "title": "블랙 스완",
      "rate": "0.5",
      "date": "2010 . 미국"
    },
    {
      "movieId": 16,
      "imageURL": "https://ssl.pstatic.net/imgmovie/mdi/mit110/1489/148909_P29_164758.jpg",
      "title": "더 페이버릿: 여왕의 여자",
      "rate": "0.5",
      "date": "2018 . 프랑스"
    },
    {
      "movieId": 19,
      "imageURL": "https://ssl.pstatic.net/imgmovie/mdi/mit110/1443/144379_P69_161321.jpg",
      "title": "러빙 빈센트",
      "rate": "0.5",
      "date": "2017 . 한국"
    },
    {
      "movieId": 20,
      "imageURL": "https://ssl.pstatic.net/imgmovie/mdi/mit110/1196/119632_P49_103013.jpg",
      "title": "위플래쉬",
      "rate": "0.5",
      "date": "2014 . 미역국"
    },
    {
      "movieId": 21,
      "imageURL": "https://ssl.pstatic.net/imgmovie/mdi/mit110/1349/134963_P15_094953.jpg",
      "title": "라라랜드",
      "rate": "0.5",
      "date": "2016 . 캐나다"
    },
    {
      "movieId": 23,
      "imageURL": "https://ssl.pstatic.net/imgmovie/mdi/mit110/0319/C1913-00.jpg",
      "title": "바닐라 스카이",
      "rate": "0.5",
      "date": "2001 . 캐나다"
    },
    {
      "movieId": 31,
      "imageURL": "https://ssl.pstatic.net/imgmovie/mdi/mit110/0378/C7888-01.jpg",
      "title": "아는 여자",
      "rate": "0.5",
      "date": "2004 . 영국"
    },
    {
      "movieId": 36,
      "imageURL": "https://ssl.pstatic.net/imgmovie/mdi/mit110/0452/45290_P59_104735.jpg",
      "title": "인터스텔라",
      "rate": "0.5",
      "date": "2014 . 미역국"
    },
    {
      "movieId": 38,
      "imageURL": "https://ssl.pstatic.net/imgmovie/mdi/mit110/1363/136315_P16_142450.jpg",
      "title": "어벤져스: 인피니티 워",
      "rate": "0.5",
      "date": "2018 . 중국"
    },
    {
      "movieId": 41,
      "imageURL": "https://ssl.pstatic.net/imgmovie/mdi/mit110/0517/51777_P39_121351.jpg",
      "title": "월드워Z",
      "rate": "0.5",
      "date": "2013 . 캐나다"
    },
    {
      "movieId": 42,
      "imageURL": "https://ssl.pstatic.net/imgmovie/mdi/mit110/0100/10048_P14_143449.jpg",
      "title": "죽은 시인의 사회",
      "rate": "0.5",
      "date": "1989 . 영국"
    },
    {
      "movieId": 43,
      "imageURL": "https://ssl.pstatic.net/imgmovie/mdi/mit110/1063/106360_P18_104023.jpg",
      "title": "위대한 쇼맨",
      "rate": "0.5",
      "date": "2017 . 미역국"
    },
    {
      "movieId": 48,
      "imageURL": "https://ssl.pstatic.net/imgmovie/mdi/mit110/0822/82239_P07_110614.jpg",
      "title": "디태치먼트",
      "rate": "0.5",
      "date": "2011 . 미역국"
    },
    {
      "movieId": 50,
      "imageURL": "https://ssl.pstatic.net/imgmovie/mdi/mit110/0368/C6858-00.jpg",
      "title": "브루스 올마이티",
      "rate": "0.5",
      "date": "2003 . 중국"
    },
    {
      "movieId": 53,
      "imageURL": "https://ssl.pstatic.net/imgmovie/mdi/mit110/0171/17159_P12_153452.jpg",
      "title": "포레스트 검프",
      "rate": "0.5",
      "date": "1994 . 헝가리"
    },
    {
      "movieId": 53,
      "imageURL": "https://ssl.pstatic.net/imgmovie/mdi/mit110/0171/17159_P12_153452.jpg",
      "title": "포레스트 검프",
      "rate": "0.5",
      "date": "1994 . 헝가리"
    }
  ]
}
